<Carts>
  <Cart cartNum="0" name="cart0" isAssigned="False" AssignedToDevice=""/>
  <Cart cartNum="1" name="cart1" isAssigned="False" AssignedToDevice=""/>
  <Cart cartNum="2" name="cart2" isAssigned="False" AssignedToDevice=""/>
  <Cart cartNum="3" name="cart3" isAssigned="False" AssignedToDevice=""/>
  <Cart cartNum="4" name="cart4" isAssigned="False" AssignedToDevice=""/>
  <Cart cartNum="5" name="cart5" isAssigned="False" AssignedToDevice=""/>
  <Cart cartNum="6" name="cart6" isAssigned="False" AssignedToDevice=""/>
  <Cart cartNum="7" name="cart7" isAssigned="False" AssignedToDevice=""/>
  <Cart cartNum="8" name="cart8" isAssigned="False" AssignedToDevice=""/>
  <Cart cartNum="9" name="cart9" isAssigned="False" AssignedToDevice=""/>
  <Cart cartNum="10" name="cart10" isAssigned="True" AssignedToDevice="a585b075-e085-4c1d-86b4-53bb50f4bb72"/>
  <Cart cartNum="11" name="cart11" isAssigned="False" AssignedToDevice=""/>
  <Cart cartNum="12" name="cart12" isAssigned="False" AssignedToDevice=""/>
  <Cart cartNum="13" name="cart13" isAssigned="False" AssignedToDevice=""/>
  <Cart cartNum="14" name="cart14" isAssigned="False" AssignedToDevice=""/>
  <Cart cartNum="15" name="cart15" isAssigned="False" AssignedToDevice=""/>
  <Cart cartNum="16" name="cart16" isAssigned="False" AssignedToDevice=""/>
  <Cart cartNum="17" name="cart17" isAssigned="False" AssignedToDevice=""/>
  <Cart cartNum="18" name="cart18" isAssigned="False" AssignedToDevice=""/>
  <Cart cartNum="19" name="cart19" isAssigned="False" AssignedToDevice=""/>
</Carts>
